{
  "$schema": "https://mintlify.com/docs.json",
  "name": "MediGuide",
  "theme": "almond",
  "colors": {
    "primary": "#f1d262",
    "light": "#7c6c34",
    "dark": "#19160b"
  },

  "logo": {
    "light": "https://media.brand.dev/60a90780-779d-4b80-a52e-b7b5166da58e.png",
    "dark": "https://media.brand.dev/60a90780-779d-4b80-a52e-b7b5166da58e.png"
  },
  "navbar": {
    "primary": {
      "type": "github",
      "href": "https://github.com/Alan-Batres/Pagina-Mediguide"
    }
  },
  "footer": {
    "socials": {
      "github": "https://github.com/Alan-Batres/Pagina-Mediguide"
    }
  },
  "navigation": {
    "tabs": [
      {
        "tab": "Documentation",
        "groups": [
          {
            "group": "Get Started",
            "pages": [
              "introduction",
              "quickstart"
            ]
          },
          {
            "group": "Features",
            "pages": [
              "features/authentication",
              "features/medical-tracking",
              "features/health-analysis",
              "features/personalized-plans"
            ]
          },
          {
            "group": "User Guides",
            "pages": [
              "guides/creating-account",
              "guides/entering-medical-data",
              "guides/understanding-results",
              "guides/password-recovery",
              "guides/legal-compliance",
              "guides/contact-support"
            ]
          }
        ]
      },
      {
        "tab": "API Reference",
        "groups": [
          {
            "group": "Overview",
            "pages": [
              "api/overview",
              "api/authentication"
            ]
          },
          {
            "group": "User Management",
            "pages": [
              "api/users/signup",
              "api/users/login",
              "api/users/forgot-password",
              "api/users/verify-reset-code",
              "api/users/reset-password"
            ]
          },
          {
            "group": "Medical Records",
            "pages": [
              "api/medical-info/create",
              "api/medical-info/get-latest"
            ]
          },
          {
            "group": "System",
            "pages": [
              "api/health-check"
            ]
          }
        ]
      }
    ]
  }
}
